understory/posts/__init__.py
understory/posts/templates/__init__.py
understory/posts/templates/activity.html
understory/posts/templates/card.html
understory/posts/templates/cards.html
understory/posts/templates/channel.html
understory/posts/templates/channels.html
understory/posts/templates/entries.html
understory/posts/templates/render_dict.html
understory/posts/templates/rooms.html
understory/posts/templates/syndication.html
understory_posts-0.0.26.dist-info/LICENSE
understory_posts-0.0.26.dist-info/WHEEL
understory_posts-0.0.26.dist-info/METADATA
understory_posts-0.0.26.dist-info/RECORD
