Metadata-Version: 2.1
Name: understory-posts
Version: 0.0.26
Summary: 
License: AGPL-3.0-or-later
Keywords: Understory,Micropub
Author: Angelo Gladding
Author-email: angelo@ragt.ag
Requires-Python: >=3.9,<3.11
Classifier: License :: OSI Approved :: GNU Affero General Public License v3 or later (AGPLv3+)
Classifier: Programming Language :: Python :: 3
Classifier: Programming Language :: Python :: 3.9
Requires-Dist: understory (>=0.0,<0.1)
